pokejdr/__init__.py
pokejdr/_version.py
pokejdr/base_stats.py
pokejdr/constants.py
pokejdr/model.py
pokejdr/data/natures_en.pkl
pokejdr/data/pokemons_en.pkl
pokejdr-0.1.0.dist-info/LICENSE
pokejdr-0.1.0.dist-info/METADATA
pokejdr-0.1.0.dist-info/WHEEL
pokejdr-0.1.0.dist-info/top_level.txt
pokejdr-0.1.0.dist-info/RECORD
