Metadata-Version: 2.1
Name: pokejdr
Version: 0.1.0
Summary: Un package utilitaire pour notre JDR pokemon.
Home-page: https://github.com/TRobine/Pkmn_Rmstrd
Author: T. Robine & F. Soubelet
Author-email: 
License: MIT
Platform: UNKNOWN
Classifier: License :: OSI Approved :: MIT License
Classifier: Natural Language :: English
Classifier: Programming Language :: Python
Classifier: Programming Language :: Python :: 3 :: Only
Classifier: Programming Language :: Python :: 3.6
Classifier: Programming Language :: Python :: 3.7
Classifier: Programming Language :: Python :: 3.8
Classifier: Programming Language :: Python :: 3.9
Requires-Python: >=3.6
Requires-Dist: numpy (>=1.19.0)
Requires-Dist: pandas (>=1.0)
Requires-Dist: loguru (>=0.5.3)
Requires-Dist: pydantic (>=1.7)
Provides-Extra: all
Requires-Dist: pytest (>=5.2) ; extra == 'all'
Requires-Dist: pytest-cov (>=2.7) ; extra == 'all'
Provides-Extra: test
Requires-Dist: pytest (>=5.2) ; extra == 'test'
Requires-Dist: pytest-cov (>=2.7) ; extra == 'test'
